<annotation>
	<folder>conference_table</folder>
	<filename>005168.jpg</filename>
	<path>/media/taru0904/8C3AC36A3AC3503E/Desktop_dump/visual-search/darknet/iCrawler_scripts/conference_table/005168.jpg</path>
	<source>
		<database>Unknown</database>
	</source>
	<size>
		<width>800</width>
		<height>533</height>
		<depth>3</depth>
	</size>
	<segmented>0</segmented>
	<object>
		<name>conference_table</name>
		<pose>Unspecified</pose>
		<truncated>0</truncated>
		<difficult>0</difficult>
		<bndbox>
			<xmin>110</xmin>
			<ymin>135</ymin>
			<xmax>637</xmax>
			<ymax>464</ymax>
		</bndbox>
	</object>
	<object>
		<name>conference_table</name>
		<pose>Unspecified</pose>
		<truncated>0</truncated>
		<difficult>0</difficult>
		<bndbox>
			<xmin>276</xmin>
			<ymin>63</ymin>
			<xmax>421</xmax>
			<ymax>130</ymax>
		</bndbox>
	</object>
	<object>
		<name>conference_table</name>
		<pose>Unspecified</pose>
		<truncated>1</truncated>
		<difficult>0</difficult>
		<bndbox>
			<xmin>578</xmin>
			<ymin>113</ymin>
			<xmax>800</xmax>
			<ymax>261</ymax>
		</bndbox>
	</object>
</annotation>
